{
"type": "FeatureCollection",
"name": "SF_route_82_NB",
"crs": { "type": "name", "properties": { "name": "urn:ogc:def:crs:OGC:1.3:CRS84" } },
"features": [
{ "type": "Feature", "properties": { "OBJECTID": 153219, "Route": 82, "RteSuffix": "", "RouteS": "82", "PMRouteID": "SF.082.R.R", "County": "SF", "District": 4, "PMPrefix": "R", "PM": 0.208, "PMSuffix": "", "PMc": "R0.208", "Odometer": 41.99399948, "PMInterval": 0.001, "HwySegment": "End County", "AlignCode": "Right", "RouteType": "State", "Direction": "NB", "PMoffset": 0.208 }, "geometry": { "type": "Point", "coordinates": [ -122.456452024999976, 37.710741106000057 ] } },
{ "type": "Feature", "properties": { "OBJECTID": 153220, "Route": 82, "RteSuffix": "", "RouteS": "82", "PMRouteID": "SF.082.R.R", "County": "SF", "District": 4, "PMPrefix": "R", "PM": 0.2, "PMSuffix": "", "PMc": "R0.2", "Odometer": 41.98600006, "PMInterval": 0.1, "HwySegment": "Mid Segment", "AlignCode": "Right", "RouteType": "State", "Direction": "NB", "PMoffset": 0.2 }, "geometry": { "type": "Point", "coordinates": [ -122.456579466, 37.710618154000031 ] } },
{ "type": "Feature", "properties": { "OBJECTID": 153221, "Route": 82, "RteSuffix": "", "RouteS": "82", "PMRouteID": "SF.082.R.R", "County": "SF", "District": 4, "PMPrefix": "R", "PM": 0.169, "PMSuffix": "", "PMc": "R0.169", "Odometer": 41.95500183, "PMInterval": 0.001, "HwySegment": "Begin Segment", "AlignCode": "Right", "RouteType": "State", "Direction": "NB", "PMoffset": 0.17 }, "geometry": { "type": "Point", "coordinates": [ -122.457057370999962, 37.710157088000074 ] } },
{ "type": "Feature", "properties": { "OBJECTID": 153222, "Route": 82, "RteSuffix": "", "RouteS": "82", "PMRouteID": "SF.082...R", "County": "SF", "District": 4, "PMPrefix": "", "PM": 0.169, "PMSuffix": "", "PMc": "0.169", "Odometer": 41.95500183, "PMInterval": 0.001, "HwySegment": "End Segment", "AlignCode": "Right", "RouteType": "State", "Direction": "NB", "PMoffset": 0.169 }, "geometry": { "type": "Point", "coordinates": [ -122.45707330099998, 37.710141719000035 ] } },
{ "type": "Feature", "properties": { "OBJECTID": 153223, "Route": 82, "RteSuffix": "", "RouteS": "82", "PMRouteID": "SF.082...R", "County": "SF", "District": 4, "PMPrefix": "", "PM": 0.1, "PMSuffix": "", "PMc": "0.1", "Odometer": 41.88600159, "PMInterval": 0.1, "HwySegment": "Mid Segment", "AlignCode": "Right", "RouteType": "State", "Direction": "NB", "PMoffset": 0.1 }, "geometry": { "type": "Point", "coordinates": [ -122.458028328999944, 37.709220325000047 ] } },
{ "type": "Feature", "properties": { "OBJECTID": 153225, "Route": 82, "RteSuffix": "", "RouteS": "82", "PMRouteID": "SF.082...R", "County": "SF", "District": 4, "PMPrefix": "", "PM": 0.0, "PMSuffix": "", "PMc": "0.0", "Odometer": 41.7859993, "PMInterval": 10.0, "HwySegment": "Begin County", "AlignCode": "Right", "RouteType": "State", "Direction": "NB", "PMoffset": 0.001 }, "geometry": { "type": "Point", "coordinates": [ -122.459047114999976, 37.708237423000071 ] } }
]
}
