{
"type": "FeatureCollection",
"name": "SM_pm_109_SB",
"crs": { "type": "name", "properties": { "name": "urn:ogc:def:crs:OGC:1.3:CRS84" } },
"features": [
{ "type": "Feature", "properties": { "OBJECTID": 203778, "Route": 109, "RteSuffix": "", "RouteS": "109", "PMRouteID": "SM.109...L", "County": "SM", "District": 4, "PMPrefix": "", "PM": 1.87, "PMSuffix": "", "PMc": "1.87", "Odometer": 0.76700002, "PMInterval": 0.01, "HwySegment": "End County", "AlignCode": "Left", "RouteType": "State", "Direction": "SB", "PMoffset": 1.87 }, "geometry": { "type": "Point", "coordinates": [ -122.142721619999975, 37.486399518000042 ] } },
{ "type": "Feature", "properties": { "OBJECTID": 203781, "Route": 109, "RteSuffix": "", "RouteS": "109", "PMRouteID": "SM.109...L", "County": "SM", "District": 4, "PMPrefix": "", "PM": 1.7999999499999999, "PMSuffix": "", "PMc": "1.8", "Odometer": 0.69700003, "PMInterval": 0.1, "HwySegment": "Mid Segment", "AlignCode": "Left", "RouteType": "State", "Direction": "SB", "PMoffset": 1.8 }, "geometry": { "type": "Point", "coordinates": [ -122.141820669999959, 37.485686711000028 ] } },
{ "type": "Feature", "properties": { "OBJECTID": 203783, "Route": 109, "RteSuffix": "", "RouteS": "109", "PMRouteID": "SM.109...L", "County": "SM", "District": 4, "PMPrefix": "", "PM": 1.7000000500000001, "PMSuffix": "", "PMc": "1.7", "Odometer": 0.597, "PMInterval": 0.1, "HwySegment": "Mid Segment", "AlignCode": "Left", "RouteType": "State", "Direction": "SB", "PMoffset": 1.7 }, "geometry": { "type": "Point", "coordinates": [ -122.141092311999955, 37.484364223000057 ] } },
{ "type": "Feature", "properties": { "OBJECTID": 203784, "Route": 109, "RteSuffix": "", "RouteS": "109", "PMRouteID": "SM.109...L", "County": "SM", "District": 4, "PMPrefix": "", "PM": 1.5, "PMSuffix": "", "PMc": "1.5", "Odometer": 0.39700001, "PMInterval": 0.1, "HwySegment": "Mid Segment", "AlignCode": "Left", "RouteType": "State", "Direction": "SB", "PMoffset": 1.5 }, "geometry": { "type": "Point", "coordinates": [ -122.139917983999965, 37.48162293300004 ] } },
{ "type": "Feature", "properties": { "OBJECTID": 203786, "Route": 109, "RteSuffix": "", "RouteS": "109", "PMRouteID": "SM.109...L", "County": "SM", "District": 4, "PMPrefix": "", "PM": 1.2999999499999999, "PMSuffix": "", "PMc": "1.3", "Odometer": 0.197, "PMInterval": 0.1, "HwySegment": "Mid Segment", "AlignCode": "Left", "RouteType": "State", "Direction": "SB", "PMoffset": 1.3 }, "geometry": { "type": "Point", "coordinates": [ -122.139750647999961, 37.478717866000068 ] } },
{ "type": "Feature", "properties": { "OBJECTID": 203787, "Route": 109, "RteSuffix": "", "RouteS": "109", "PMRouteID": "SM.109...L", "County": "SM", "District": 4, "PMPrefix": "", "PM": 1.2000000500000001, "PMSuffix": "", "PMc": "1.2", "Odometer": 0.097, "PMInterval": 0.1, "HwySegment": "Mid Segment", "AlignCode": "Left", "RouteType": "State", "Direction": "SB", "PMoffset": 1.2 }, "geometry": { "type": "Point", "coordinates": [ -122.139708662999965, 37.477254531000028 ] } },
{ "type": "Feature", "properties": { "OBJECTID": 203788, "Route": 109, "RteSuffix": "", "RouteS": "109", "PMRouteID": "SM.109...L", "County": "SM", "District": 4, "PMPrefix": "", "PM": 1.10300004, "PMSuffix": "", "PMc": "1.103", "Odometer": 0.0, "PMInterval": 0.001, "HwySegment": "Begin County", "AlignCode": "Left", "RouteType": "State", "Direction": "SB", "PMoffset": 1.104 }, "geometry": { "type": "Point", "coordinates": [ -122.139674088999982, 37.475929876000066 ] } },
{ "type": "Feature", "properties": { "OBJECTID": 204304, "Route": 109, "RteSuffix": "", "RouteS": "109", "PMRouteID": "SM.109...L", "County": "SM", "District": 4, "PMPrefix": "", "PM": 1.39999998, "PMSuffix": "", "PMc": "1.4", "Odometer": 0.29699999, "PMInterval": 0.1, "HwySegment": "Mid Segment", "AlignCode": "Left", "RouteType": "State", "Direction": "SB", "PMoffset": 1.4 }, "geometry": { "type": "Point", "coordinates": [ -122.139782256999979, 37.480178708000039 ] } },
{ "type": "Feature", "properties": { "OBJECTID": 204718, "Route": 109, "RteSuffix": "", "RouteS": "109", "PMRouteID": "SM.109...L", "County": "SM", "District": 4, "PMPrefix": "", "PM": 1.60000002, "PMSuffix": "", "PMc": "1.6", "Odometer": 0.49700001, "PMInterval": 0.1, "HwySegment": "Mid Segment", "AlignCode": "Left", "RouteType": "State", "Direction": "SB", "PMoffset": 1.6 }, "geometry": { "type": "Point", "coordinates": [ -122.14046828, 37.483002450000072 ] } }
]
}
