{
"type": "FeatureCollection",
"name": "SD_route_282_WB",
"crs": { "type": "name", "properties": { "name": "urn:ogc:def:crs:OGC:1.3:CRS84" } },
"features": [
{ "type": "Feature", "properties": { "OBJECTID": 286320, "Route": 282, "RteSuffix": "", "RouteS": "282", "PMRouteID": "SD.282..RR", "County": "SD", "District": 11, "PMPrefix": "", "PM": 0.69099998, "PMSuffix": "R", "PMc": "0.691R", "Odometer": 0.69099998, "PMInterval": 0.001, "HwySegment": "End County", "AlignCode": "Right Independent", "RouteType": "State", "Direction": "WB", "PMoffset": 0.691 }, "geometry": { "type": "Point", "coordinates": [ -117.183815409999966, 32.698152219000065 ] } },
{ "type": "Feature", "properties": { "OBJECTID": 286322, "Route": 282, "RteSuffix": "", "RouteS": "282", "PMRouteID": "SD.282..RR", "County": "SD", "District": 11, "PMPrefix": "", "PM": 0.60000001999999997, "PMSuffix": "R", "PMc": "0.6R", "Odometer": 0.60000001999999997, "PMInterval": 0.1, "HwySegment": "Mid Segment", "AlignCode": "Right Independent", "RouteType": "State", "Direction": "WB", "PMoffset": 0.6 }, "geometry": { "type": "Point", "coordinates": [ -117.18308992599998, 32.699393891000057 ] } },
{ "type": "Feature", "properties": { "OBJECTID": 286323, "Route": 282, "RteSuffix": "", "RouteS": "282", "PMRouteID": "SD.282..RR", "County": "SD", "District": 11, "PMPrefix": "", "PM": 0.40000001000000002, "PMSuffix": "R", "PMc": "0.4R", "Odometer": 0.40000001000000002, "PMInterval": 0.1, "HwySegment": "Mid Segment", "AlignCode": "Right Independent", "RouteType": "State", "Direction": "WB", "PMoffset": 0.4 }, "geometry": { "type": "Point", "coordinates": [ -117.180087840999988, 32.698457286000064 ] } },
{ "type": "Feature", "properties": { "OBJECTID": 286325, "Route": 282, "RteSuffix": "", "RouteS": "282", "PMRouteID": "SD.282..RR", "County": "SD", "District": 11, "PMPrefix": "", "PM": 0.30000000999999998, "PMSuffix": "R", "PMc": "0.3R", "Odometer": 0.30000000999999998, "PMInterval": 0.1, "HwySegment": "Mid Segment", "AlignCode": "Right Independent", "RouteType": "State", "Direction": "WB", "PMoffset": 0.3 }, "geometry": { "type": "Point", "coordinates": [ -117.178570542999978, 32.697827971000038 ] } },
{ "type": "Feature", "properties": { "OBJECTID": 286327, "Route": 282, "RteSuffix": "", "RouteS": "282", "PMRouteID": "SD.282..RR", "County": "SD", "District": 11, "PMPrefix": "", "PM": 0.2, "PMSuffix": "R", "PMc": "0.2R", "Odometer": 0.2, "PMInterval": 0.1, "HwySegment": "Mid Segment", "AlignCode": "Right Independent", "RouteType": "State", "Direction": "WB", "PMoffset": 0.2 }, "geometry": { "type": "Point", "coordinates": [ -117.177066983999964, 32.697192760000064 ] } },
{ "type": "Feature", "properties": { "OBJECTID": 286328, "Route": 282, "RteSuffix": "", "RouteS": "282", "PMRouteID": "SD.282..RR", "County": "SD", "District": 11, "PMPrefix": "", "PM": 0.0, "PMSuffix": "R", "PMc": "0.0R", "Odometer": 0.0, "PMInterval": 10.0, "HwySegment": "Begin County", "AlignCode": "Right Independent", "RouteType": "State", "Direction": "WB", "PMoffset": 0.001 }, "geometry": { "type": "Point", "coordinates": [ -117.174035759, 32.695927716000028 ] } },
{ "type": "Feature", "properties": { "OBJECTID": 287483, "Route": 282, "RteSuffix": "", "RouteS": "282", "PMRouteID": "SD.282..RR", "County": "SD", "District": 11, "PMPrefix": "", "PM": 0.5, "PMSuffix": "R", "PMc": "0.5R", "Odometer": 0.5, "PMInterval": 0.1, "HwySegment": "Mid Segment", "AlignCode": "Right Independent", "RouteType": "State", "Direction": "WB", "PMoffset": 0.5 }, "geometry": { "type": "Point", "coordinates": [ -117.181694653999955, 32.699127150000038 ] } },
{ "type": "Feature", "properties": { "OBJECTID": 288155, "Route": 282, "RteSuffix": "", "RouteS": "282", "PMRouteID": "SD.282..RR", "County": "SD", "District": 11, "PMPrefix": "", "PM": 0.1, "PMSuffix": "R", "PMc": "0.1R", "Odometer": 0.1, "PMInterval": 0.1, "HwySegment": "Mid Segment", "AlignCode": "Right Independent", "RouteType": "State", "Direction": "WB", "PMoffset": 0.1 }, "geometry": { "type": "Point", "coordinates": [ -117.175522827999941, 32.69654679000007 ] } }
]
}
