{
"type": "FeatureCollection",
"name": "HUM_pm_271_NB",
"crs": { "type": "name", "properties": { "name": "urn:ogc:def:crs:OGC:1.3:CRS84" } },
"features": [
{ "type": "Feature", "properties": { "OBJECTID": 278175, "Route": 271, "RteSuffix": "", "RouteS": "271", "PMRouteID": "HUM271.T.R", "County": "HUM", "District": 1, "PMPrefix": "T", "PM": 0.30599999, "PMSuffix": "", "PMc": "T0.306", "Odometer": 14.8380003, "PMInterval": 0.001, "HwySegment": "End County", "AlignCode": "Right", "RouteType": "State", "Direction": "NB", "PMoffset": 0.306 }, "geometry": { "type": "Point", "coordinates": [ -123.780353697999942, 40.00201400800006 ] } },
{ "type": "Feature", "properties": { "OBJECTID": 278176, "Route": 271, "RteSuffix": "", "RouteS": "271", "PMRouteID": "HUM271.T.R", "County": "HUM", "District": 1, "PMPrefix": "T", "PM": 0.116, "PMSuffix": "", "PMc": "T0.116", "Odometer": 14.64799976, "PMInterval": 0.001, "HwySegment": "Begin Segment", "AlignCode": "Right", "RouteType": "State", "Direction": "NB", "PMoffset": 0.117 }, "geometry": { "type": "Point", "coordinates": [ -123.783895500999961, 40.002963589000046 ] } },
{ "type": "Feature", "properties": { "OBJECTID": 278177, "Route": 271, "RteSuffix": "", "RouteS": "271", "PMRouteID": "HUM271...R", "County": "HUM", "District": 1, "PMPrefix": "", "PM": 0.116, "PMSuffix": "", "PMc": "0.116", "Odometer": 14.64799976, "PMInterval": 0.001, "HwySegment": "End Segment", "AlignCode": "Right", "RouteType": "State", "Direction": "NB", "PMoffset": 0.116 }, "geometry": { "type": "Point", "coordinates": [ -123.783916119999958, 40.00295716200003 ] } },
{ "type": "Feature", "properties": { "OBJECTID": 278178, "Route": 271, "RteSuffix": "", "RouteS": "271", "PMRouteID": "HUM271...R", "County": "HUM", "District": 1, "PMPrefix": "", "PM": 0.1, "PMSuffix": "", "PMc": "0.1", "Odometer": 14.63199997, "PMInterval": 0.1, "HwySegment": "Mid Segment", "AlignCode": "Right", "RouteType": "State", "Direction": "NB", "PMoffset": 0.1 }, "geometry": { "type": "Point", "coordinates": [ -123.784224428999948, 40.00282435400004 ] } },
{ "type": "Feature", "properties": { "OBJECTID": 278179, "Route": 271, "RteSuffix": "", "RouteS": "271", "PMRouteID": "HUM271...R", "County": "HUM", "District": 1, "PMPrefix": "", "PM": 0.0, "PMSuffix": "", "PMc": "0.0", "Odometer": 14.53199959, "PMInterval": 10.0, "HwySegment": "Begin County", "AlignCode": "Right", "RouteType": "State", "Direction": "NB", "PMoffset": 0.001 }, "geometry": { "type": "Point", "coordinates": [ -123.785971908999954, 40.001793664000047 ] } },
{ "type": "Feature", "properties": { "OBJECTID": 278515, "Route": 271, "RteSuffix": "", "RouteS": "271", "PMRouteID": "HUM271.T.R", "County": "HUM", "District": 1, "PMPrefix": "T", "PM": 0.30000000999999998, "PMSuffix": "", "PMc": "T0.3", "Odometer": 14.83199978, "PMInterval": 0.1, "HwySegment": "Mid Segment", "AlignCode": "Right", "RouteType": "State", "Direction": "NB", "PMoffset": 0.3 }, "geometry": { "type": "Point", "coordinates": [ -123.780395253, 40.002111213000035 ] } },
{ "type": "Feature", "properties": { "OBJECTID": 281006, "Route": 271, "RteSuffix": "", "RouteS": "271", "PMRouteID": "HUM271.T.R", "County": "HUM", "District": 1, "PMPrefix": "T", "PM": 0.2, "PMSuffix": "", "PMc": "T0.2", "Odometer": 14.73200035, "PMInterval": 0.1, "HwySegment": "Mid Segment", "AlignCode": "Right", "RouteType": "State", "Direction": "NB", "PMoffset": 0.2 }, "geometry": { "type": "Point", "coordinates": [ -123.782243251999944, 40.002638345000037 ] } }
]
}
